kkblinka/__init__.py
kkblinka-0.0.2.dist-info/LICENSE
kkblinka-0.0.2.dist-info/METADATA
kkblinka-0.0.2.dist-info/WHEEL
kkblinka-0.0.2.dist-info/top_level.txt
kkblinka-0.0.2.dist-info/RECORD
